dm_haiku-0.0.15.dist-info/licenses/LICENSE
docs/conf.py
docs/ext/coverage_check.py
examples/imagenet/__init__.py
examples/imagenet/dataset.py
examples/imagenet/train.py
examples/impala/__init__.py
examples/impala/actor.py
examples/impala/actor_test.py
examples/impala/agent.py
examples/impala/haiku_nets.py
examples/impala/learner.py
examples/impala/learner_test.py
examples/impala/run_catch.py
examples/impala/util.py
examples/rnn/__init__.py
examples/rnn/dataset.py
examples/rnn/train.py
examples/transformer/__init__.py
examples/transformer/dataset.py
examples/transformer/model.py
examples/transformer/train.py
haiku/__init__.py
haiku/config.py
haiku/data_structures.py
haiku/initializers.py
haiku/mixed_precision.py
haiku/nets.py
haiku/pad.py
haiku/py.typed
haiku/testing.py
haiku/typing.py
haiku/_src/__init__.py
haiku/_src/analytics.py
haiku/_src/attention.py
haiku/_src/attention_test.py
haiku/_src/base.py
haiku/_src/base_test.py
haiku/_src/basic.py
haiku/_src/basic_test.py
haiku/_src/batch_norm.py
haiku/_src/batch_norm_test.py
haiku/_src/bias.py
haiku/_src/bias_test.py
haiku/_src/config.py
haiku/_src/config_test.py
haiku/_src/conv.py
haiku/_src/conv_test.py
haiku/_src/data_structures.py
haiku/_src/data_structures_test.py
haiku/_src/deferred.py
haiku/_src/deferred_test.py
haiku/_src/depthwise_conv.py
haiku/_src/depthwise_conv_test.py
haiku/_src/dot.py
haiku/_src/dot_test.py
haiku/_src/embed.py
haiku/_src/embed_test.py
haiku/_src/eval_shape.py
haiku/_src/eval_shape_test.py
haiku/_src/filtering.py
haiku/_src/filtering_test.py
haiku/_src/group_norm.py
haiku/_src/group_norm_test.py
haiku/_src/initializers.py
haiku/_src/initializers_test.py
haiku/_src/jaxpr_info.py
haiku/_src/jaxpr_info_test.py
haiku/_src/layer_norm.py
haiku/_src/layer_norm_test.py
haiku/_src/layer_stack.py
haiku/_src/layer_stack_test.py
haiku/_src/lift.py
haiku/_src/lift_test.py
haiku/_src/mixed_precision.py
haiku/_src/mixed_precision_test.py
haiku/_src/module.py
haiku/_src/module_test.py
haiku/_src/moving_averages.py
dm_haiku-0.0.15.dist-info/METADATA
dm_haiku-0.0.15.dist-info/WHEEL
dm_haiku-0.0.15.dist-info/top_level.txt
dm_haiku-0.0.15.dist-info/RECORD
