Metadata-Version: 2.4
Name: dm-haiku
Version: 0.0.15
Summary: Haiku is a library for building neural networks in JAX.
Home-page: https://github.com/deepmind/dm-haiku
Author: DeepMind
Author-email: haiku-dev-os@google.com
License: Apache 2.0
Classifier: Development Status :: 4 - Beta
Classifier: Intended Audience :: Developers
Classifier: Intended Audience :: Education
Classifier: Intended Audience :: Science/Research
Classifier: License :: OSI Approved :: Apache Software License
Classifier: Programming Language :: Python :: 3
Classifier: Programming Language :: Python :: 3.10
Classifier: Programming Language :: Python :: 3.11
Classifier: Topic :: Scientific/Engineering :: Mathematics
Classifier: Topic :: Software Development :: Libraries :: Python Modules
Classifier: Topic :: Software Development :: Libraries
Requires-Python: >=3.10
License-File: LICENSE
Requires-Dist: absl-py>=0.7.1
Requires-Dist: jmp>=0.0.2
Requires-Dist: numpy>=1.18.0
Requires-Dist: tabulate>=0.8.9
Provides-Extra: jax
Requires-Dist: jax>=0.7.2; extra == "jax"
Requires-Dist: jaxlib>=0.7.2; extra == "jax"
Provides-Extra: flax
Requires-Dist: flax>=0.7.1; extra == "flax"
Dynamic: author
Dynamic: author-email
Dynamic: classifier
Dynamic: description
Dynamic: description-content-type
Dynamic: home-page
Dynamic: license
Dynamic: license-file
Dynamic: provides-extra
Dynamic: requires-dist
Dynamic: requires-python
Dynamic: summary
